gxmmx_flow_core_test/__init__.py
gxmmx_flow_core_test/codequality.py
gxmmx_flow_core_test/core.py
gxmmx_flow_core_test/errors.py
gxmmx_flow_core_test/log.py
gxmmx_flow_core_test-0.1.0.dist-info/METADATA
gxmmx_flow_core_test-0.1.0.dist-info/WHEEL
gxmmx_flow_core_test-0.1.0.dist-info/RECORD
