Metadata-Version: 2.1
Name: gxmmx-flow-core-test
Version: 0.1.0
Summary: GxMMx Flow core functionality
Home-page: https://gitlab.com/gxmmx/gitops/flow/core/flow-core-test
License: MIT
Keywords: gxmmx,flow,core,library,cicd,workflow
Author: Gudmundur Gudmundsson
Author-email: gummigudm@gmail.com
Maintainer: Gudmundur Gudmundsson
Maintainer-email: gummigudm@gmail.com
Requires-Python: >=3.11,<4.0
Classifier: License :: OSI Approved :: MIT License
Classifier: Programming Language :: Python :: 3
Classifier: Programming Language :: Python :: 3.11
Classifier: Programming Language :: Python :: 3.12
Requires-Dist: pyyaml (>=6.0.2,<7.0.0)
Project-URL: Documentation, https://gitlab.com/gxmmx/gitops/flow/core/flow-core-test/-/blob/main/README.md
Project-URL: Repository, https://gitlab.com/gxmmx/gitops/flow/core/flow-core-test
